super_scad_cone/SmoothCone.py
super_scad_cone/SmoothCylinder.py
super_scad_cone/__init__.py
super_scad_cone-0.10.1.dist-info/LICENSE
super_scad_cone-0.10.1.dist-info/METADATA
super_scad_cone-0.10.1.dist-info/WHEEL
super_scad_cone-0.10.1.dist-info/RECORD
