Metadata-Version: 2.1
Name: Super-SCAD-Cone
Version: 0.10.1
Summary: SuperSCAD widgets for cones and cylinders with smooth edges.
Home-page: https://github.com/SuperSCAD/Cone
License: MIT
Keywords: OpenSCAD,SuperSCAD,Cone,Cylinder
Author: P.R. Water
Author-email: p.r.water@setbased.nl
Requires-Python: >=3.10.0,<4.0.0
Classifier: Development Status :: 5 - Production/Stable
Classifier: Intended Audience :: Developers
Classifier: Intended Audience :: Manufacturing
Classifier: License :: OSI Approved :: MIT License
Classifier: Programming Language :: Python :: 3
Classifier: Programming Language :: Python :: 3.10
Classifier: Programming Language :: Python :: 3.11
Classifier: Programming Language :: Python :: 3.12
Classifier: Programming Language :: Python :: 3.13
Classifier: Topic :: Multimedia :: Graphics :: 3D Modeling
Classifier: Topic :: Software Development :: Code Generators
Requires-Dist: super-scad (>=0.10.3,<0.11.0)
Requires-Dist: super-scad-polygon (>=0.9.7,<0.10.0)
Requires-Dist: super-scad-smooth-profile (>=0.6.2,<0.7.0)
Project-URL: Documentation, https://superscad.readthedocs.io/
Project-URL: Repository, https://github.com/SuperSCAD/Cone
